{
  "news": [
    {
      "name": "경제",
      "url": "https://news.naver.com/section/101",
      "category": "news",
      "data": [
        {
          "link": "https://n.news.naver.com/mnews/article/003/0012884645",
          "title": "\"719만원이던 월급이 66만원\"…현대트랜시스 직원들의 고충"
        },
        {
          "link": "https://n.news.naver.com/mnews/article/056/0011831891",
          "title": "삼성, AI 포럼 비공개 개최…“글로벌 석학과 AI 미래 논의”"
        },
        {
          "link": "https://n.news.naver.com/mnews/article/014/0005262905",
          "title": "젠슨 황 \"HBM4 공급 더 빨리\"… SK·엔비디아 ‘AI동맹’ 굳건"
        },
        {
          "link": "https://n.news.naver.com/mnews/article/374/0000409328",
          "title": "서초 그린벨트에 2만호 짓는다…고양·의왕·의정부에 3만호"
        },
        {
          "link": "https://n.news.naver.com/mnews/article/015/0005052998",
          "title": "[속보] 10월 소비자물가 1.3% 상승…3년 9개월 만에 최저"
        },
        {
          "link": "https://n.news.naver.com/mnews/article/018/0005877800",
          "title": "롯데칠성음료, 3분기 영업이익 787억…전년대비 6.6% 감소"
        },
        {
          "link": "https://n.news.naver.com/mnews/article/243/0000067471",
          "title": "한국피자헛, 회생절차 밟는다...차액가맹금 소송 패소 영향"
        },
        {
          "link": "https://n.news.naver.com/mnews/article/214/0001384629",
          "title": "인스타그램 '10대 계정' 내년 1월 국내 출시…\"부모가 관리감독\""
        },
        {
          "link": "https://n.news.naver.com/mnews/article/277/0005495461",
          "title": "카카오페이 \"PG·해외사 M&A 검토…11월 개인연금저축 출시\""
        },
        {
          "link": "https://n.news.naver.com/mnews/article/014/0005263120",
          "title": "한화시스템-HJ중공업 '글로벌 함정시장 진출' 맞손"
        }
      ]
    },
    {
      "name": "사회",
      "url": "https://news.naver.com/section/102",
      "category": "news",
      "data": [
        {
          "link": "https://n.news.naver.com/mnews/article/214/0001384417",
          "title": "북한강 '훼손 시신' 유기 피의자는 군 장교‥\"말다툼하다 살해\""
        },
        {
          "link": "https://n.news.naver.com/mnews/article/002/0002357829",
          "title": "부산시의회 325회 정례회 개최...행정감사 이어 예산안 심사"
        },
        {
          "link": "https://n.news.naver.com/mnews/article/052/0002109591",
          "title": "문체부 \"감독 선임, 절차적 하자...정몽규 포함 3명 자격정지 이상 중징계 요구\""
        },
        {
          "link": "https://n.news.naver.com/mnews/article/001/0015025436",
          "title": "검찰, '공천 개입' 명태균 창원지검 수사팀 증원…3명 안팎"
        },
        {
          "link": "https://n.news.naver.com/mnews/article/366/0001029743",
          "title": "서울시, ‘킥보드 없는 거리’ 지정…전국 최초"
        },
        {
          "link": "https://n.news.naver.com/mnews/article/014/0005263477",
          "title": "전남도, 2025년 지방소멸대응기금 총 1632억원 확보...4년 연속 전국 최다"
        },
        {
          "link": "https://n.news.naver.com/mnews/article/008/0005110377",
          "title": "시흥시, 서울대·한전과 송전선로 협약…임병택 \"불가피한 선택\""
        },
        {
          "link": "https://n.news.naver.com/mnews/article/055/0001203268",
          "title": "김영선 이틀째 조사…명태균 며칠 내 소환할 듯"
        },
        {
          "link": "https://n.news.naver.com/mnews/article/009/0005391211",
          "title": "[단독] “가짜 서류면 다 돼”…20억원대 치아보험 사기 일당 ‘덜미’"
        },
        {
          "link": "https://n.news.naver.com/mnews/article/421/0007889170",
          "title": "\"징역 가겠다\"…음주운전 사고 후 생방송 한 BJ 입건"
        }
      ]
    },
    {
      "name": "생활/문화",
      "url": "https://news.naver.com/section/103",
      "category": "news",
      "data": [
        {
          "link": "https://n.news.naver.com/mnews/article/469/0000831535",
          "title": "올해 대산문학상, 시인 강은교·소설가 김희선·평론가 서영채·번역가 말도나도가 받는다"
        },
        {
          "link": "https://n.news.naver.com/mnews/article/374/0000409284",
          "title": "출근길 '초겨울' 날씨…곳곳 서리[내일 날씨]"
        },
        {
          "link": "https://n.news.naver.com/mnews/article/437/0000417043",
          "title": "한국 '장 담그기' 문화, 유네스코 인류무형유산 등재 유력"
        },
        {
          "link": "https://n.news.naver.com/mnews/article/648/0000030372",
          "title": "기아 스포티지, 디자인·주행 개선됐다…판매가 300만원↑"
        },
        {
          "link": "https://n.news.naver.com/mnews/article/018/0005877809",
          "title": "롯데렌탈 3분기 영업익 805억…'사업 모델 전환 영향' 전년比 1.2%↓"
        },
        {
          "link": "https://n.news.naver.com/mnews/article/008/0005110159",
          "title": "민희진 \"투자·계약 논의 모두 사실 무근…헛소문 원천봉쇄\""
        },
        {
          "link": "https://n.news.naver.com/mnews/article/009/0005390962",
          "title": "113년만의 귀향...고향 원주에 다시 선 ‘국보’ 법천사지 지광국사탑"
        },
        {
          "link": "https://n.news.naver.com/mnews/article/055/0001203560",
          "title": "심청이·춘향이·놀보가 한 무대에…국립극장 '마당놀이 모듬전'"
        }
      ]
    },
    {
      "name": "IT/과학",
      "url": "https://news.naver.com/section/105",
      "category": "news",
      "data": [
        {
          "link": "https://n.news.naver.com/mnews/article/277/0005495195",
          "title": "노션, '마켓플레이스' '폼' '메일' 등 신규 기능 공개…\"개인 맞춤형 협업 툴\""
        },
        {
          "link": "https://n.news.naver.com/mnews/article/009/0005391214",
          "title": "“지니야 임영웅 노래 장면 보여줘”…KT, 인공지능 셋톱박스 공개"
        },
        {
          "link": "https://n.news.naver.com/mnews/article/008/0005110133",
          "title": "韓-美 공동 개발 '태양 코로나그래프' 발사…오늘 밤 우주정거장 도착"
        },
        {
          "link": "https://n.news.naver.com/mnews/article/025/0003398472",
          "title": "광고주에 98만명 민감정보 넘긴 메타, 과징금 216억"
        },
        {
          "link": "https://n.news.naver.com/mnews/article/421/0007889191",
          "title": "KT, 자회사 설립 준비 본격화…1700여명 전출 신청"
        },
        {
          "link": "https://n.news.naver.com/mnews/article/055/0001203327",
          "title": "3분기 태블릿PC 시장 20% 성장…애플 주춤, 삼성·아마존 약진"
        },
        {
          "link": "https://n.news.naver.com/mnews/article/421/0007887341",
          "title": "\"정부·민간 힘 모으면 AI 3대 강국 도약 가능\""
        },
        {
          "link": "https://n.news.naver.com/mnews/article/009/0005391302",
          "title": "슈퍼컴 6호기 서비스 개시 1년 미뤄져...예산 1500억원 늘렸다"
        }
      ]
    },
    {
      "name": "세계",
      "url": "https://news.naver.com/section/104",
      "category": "news",
      "data": [
        {
          "link": "https://n.news.naver.com/mnews/article/052/0002109636",
          "title": "일 경제단체 \"한국처럼 비자 면제\" 중국에 요청"
        },
        {
          "link": "https://n.news.naver.com/mnews/article/001/0015025475",
          "title": "더힐 \"트럼프,경합주 4승2무1패\"…NPR \"전국선 해리스 4%p 우위\"(종합)[美대선]"
        },
        {
          "link": "https://n.news.naver.com/mnews/article/052/0002109765",
          "title": "러시아 \"미 대선 누가 당선되든 신경 안 쓴다\""
        },
        {
          "link": "https://n.news.naver.com/mnews/article/052/0002109648",
          "title": "경복궁서 요가 하는 베트남 레깅스 女…\"수치스럽다\" vs \"존중해야\""
        },
        {
          "link": "https://n.news.naver.com/mnews/article/079/0003955266",
          "title": "우크라 당국, 북한군과 교전시작 '이미 우리 공격 받았다'"
        },
        {
          "link": "https://n.news.naver.com/mnews/article/421/0007886980",
          "title": "푸틴, 최선희 북한 외무상과 회담…\"예정없던 갑작스러운 만남\"(상보)"
        },
        {
          "link": "https://n.news.naver.com/mnews/article/015/0005053497",
          "title": "\"트럼프가 이긴다\"…'스타 새끼 하마' 무뎅의 예측 [2024 美대선]"
        },
        {
          "link": "https://n.news.naver.com/mnews/article/214/0001384626",
          "title": "\"해리스·트럼프, 마지막날까지 접전‥승률분석 50대 50\""
        },
        {
          "link": "https://n.news.naver.com/mnews/article/001/0015027323",
          "title": "[영상] \"소고기 많네, 완전 짱\"…러 파병 북한군이 중국말을?"
        },
        {
          "link": "https://n.news.naver.com/mnews/article/052/0002109270",
          "title": "미 공화당, 상원 다수당 되나...한국계 첫 상원의원 탄생 기대"
        }
      ]
    }
  ],
  "social": [
    {
      "name": "AAGAG",
      "url": "https://aagag.com",
      "category": "social",
      "priority": 1,
      "data": [
        {
          "link": "https://aagag.com/mirror/re.php?ss=fmkorea_7659513147",
          "title": "좀 짜치는 코카콜라 근황.jpg"
        },
        {
          "link": "https://aagag.com/mirror/re.php?ss=fmkorea_7659491250",
          "title": "지디 인스타 스토리 근황"
        },
        {
          "link": "https://aagag.com/mirror/re.php?ss=fmkorea_7659584970",
          "title": "놀이터 시끄럽다 신고한 아들 어머니가 꾸짖자 무참히 살해..\"난 촉법, 일본에 가서 살겠다\""
        },
        {
          "link": "https://aagag.com/mirror/re.php?ss=bobae_6337051",
          "title": "윤정부, 초유의 사태 ㄷㄷ"
        },
        {
          "link": "https://aagag.com/mirror/re.php?ss=ruli_68304074",
          "title": "미국 대선 한국의 트럼프 지지자들 현재 상황..;;"
        },
        {
          "link": "https://aagag.com/mirror/re.php?ss=ppomppu_9026358",
          "title": "요즘) 신축 아파트 문화 충격 ㄷ..jpg"
        },
        {
          "link": "https://aagag.com/mirror/re.php?ss=mlbpark_202411050098943081",
          "title": "오사카 근황 ㄷㄷ"
        },
        {
          "link": "https://aagag.com/mirror/re.php?ss=ppomppu_9026332",
          "title": "부활한 일본 AV계의 전설적인 거물.avi"
        },
        {
          "link": "https://aagag.com/mirror/re.php?ss=humor_1336101",
          "title": "19) 싱글벙글 휴대폰 허용된 군대 화장실 상황.jpg"
        },
        {
          "link": "https://aagag.com/mirror/re.php?ss=ppomppu_9026321",
          "title": "35살 박보영 ㄷ..jpg"
        },
        {
          "link": "https://aagag.com/mirror/re.php?ss=mlbpark_202411050098943102",
          "title": "안성재 근황 jpg."
        },
        {
          "link": "https://aagag.com/mirror/re.php?ss=mlbpark_202411050098943216",
          "title": "갤럭시 광고 비공개 됐네요 ㅋㅋㅋ"
        },
        {
          "link": "https://aagag.com/mirror/re.php?ss=ruli_68304453",
          "title": "김태희씨가 팔고있다는 유명한 1,000원 빵!"
        },
        {
          "link": "https://aagag.com/mirror/re.php?ss=slrclub_40948216",
          "title": "윤석열 정상 판정 ㄷㄷㄷㄷ"
        },
        {
          "link": "https://aagag.com/mirror/re.php?ss=bobae_6337048",
          "title": "퇴진집회 시민단체 압수수색ㅋㅋㅋㅋㅋ"
        },
        {
          "link": "https://aagag.com/mirror/re.php?ss=slrclub_40948193",
          "title": "470억을 거절한 샤킬 오닐 ㄷㄷㄷ"
        },
        {
          "link": "https://aagag.com/mirror/re.php?ss=humor_1336103",
          "title": "75G 컵을 만져본 디씨인 ㄷㄷㄷ"
        },
        {
          "link": "https://aagag.com/mirror/re.php?ss=bobae_6337069",
          "title": "죄벌 2세 돈 펑펑 쓰는법"
        },
        {
          "link": "https://aagag.com/mirror/re.php?ss=ddanzi_823802295",
          "title": "미국 대선 판도.. 오늘 아침 회사 출근자들 투표 동향"
        },
        {
          "link": "https://aagag.com/mirror/re.php?ss=ruli_68304564",
          "title": "경험이 풍부한 여사친.manhwa"
        },
        {
          "link": "https://aagag.com/mirror/re.php?ss=ddanzi_823803137",
          "title": "편의점중 망해가고있는 브랜드.JPG"
        },
        {
          "link": "https://aagag.com/mirror/re.php?ss=etoland_4713099",
          "title": "삼성 마케팅팀이 데려와야할 인재"
        },
        {
          "link": "https://aagag.com/mirror/re.php?ss=inven_2347058",
          "title": "좋소기업 에이스의 근무태도 논란"
        },
        {
          "link": "https://aagag.com/mirror/re.php?ss=82cook_3909173",
          "title": "서울법대 79동기 “석열아, 더 나빠질 것도 없다. 소신껏 해라.."
        },
        {
          "link": "https://aagag.com/mirror/re.php?ss=clien_18834462",
          "title": "사우디 네옴시티, 원안 170km에서 2.4km로 목표 변경"
        },
        {
          "link": "https://aagag.com/mirror/re.php?ss=ppomppu_9026375",
          "title": "현 세계에서 젤 인기 많은 보디빌더 은퇴"
        },
        {
          "link": "https://aagag.com/mirror/re.php?ss=82cook_3909193",
          "title": "PD수첩,, 와...보다가 정신 나가겠네요"
        },
        {
          "link": "https://aagag.com/mirror/re.php?ss=humor_1336110",
          "title": "ㅇㅎ)20살 연상녀한테 빠지는 이유"
        },
        {
          "link": "https://aagag.com/mirror/re.php?ss=inven_2347063",
          "title": "요즘 그래픽카드 미쳐버린 크기 체감 ㄷㄷ"
        },
        {
          "link": "https://aagag.com/mirror/re.php?ss=inven_2347084",
          "title": "처제랑 결혼하고 싶습니다"
        },
        {
          "link": "https://aagag.com/mirror/re.php?ss=clien_18834484",
          "title": "PD 수첩 내용 짠하네요.."
        },
        {
          "link": "https://aagag.com/mirror/re.php?ss=ddanzi_823802552",
          "title": "펌) 어느 사진가가 찍은 사슴 사진.jpg"
        }
      ]
    }
  ],
  "culture": [
    {
      "name": "Kinolights Ranking",
      "url": "https://m.kinolights.com/ranking/kino",
      "category": "culture",
      "priority": 4,
      "isRanking": true,
      "data": [
        {
          "link": "https://m.kinolights.com/title/116754",
          "title": "정년이"
        },
        {
          "link": "https://m.kinolights.com/title/117295",
          "title": "지옥 시즌 2"
        },
        {
          "link": "https://m.kinolights.com/title/134887",
          "title": "이토록 친밀한 배신자"
        },
        {
          "link": "https://m.kinolights.com/title/135692",
          "title": "지옥에서 온 판사"
        },
        {
          "link": "https://m.kinolights.com/title/102316",
          "title": "탈주"
        },
        {
          "link": "https://m.kinolights.com/title/136118",
          "title": "정숙한 세일즈"
        },
        {
          "link": "https://m.kinolights.com/title/116620",
          "title": "더 퍼스트 슬램덩크"
        },
        {
          "link": "https://m.kinolights.com/title/96350",
          "title": "베놈 2: 렛 데어 비 카니지"
        },
        {
          "link": "https://m.kinolights.com/title/130293",
          "title": "조립식 가족"
        },
        {
          "link": "https://m.kinolights.com/title/137616",
          "title": "돈 무브"
        },
        {
          "link": "https://m.kinolights.com/title/129477",
          "title": "사랑 후에 오는 것들"
        },
        {
          "link": "https://m.kinolights.com/title/136900",
          "title": "생존왕"
        },
        {
          "link": "https://m.kinolights.com/title/116165",
          "title": "좋거나 나쁜 동재"
        },
        {
          "link": "https://m.kinolights.com/title/80205",
          "title": "열혈사제"
        },
        {
          "link": "https://m.kinolights.com/title/136826",
          "title": "대도시의 사랑법"
        },
        {
          "link": "https://m.kinolights.com/title/134780",
          "title": "베놈: 라스트 댄스"
        },
        {
          "link": "https://m.kinolights.com/title/64146",
          "title": "베놈"
        },
        {
          "link": "https://m.kinolights.com/title/6051",
          "title": "해리 포터와 마법사의 돌"
        },
        {
          "link": "https://m.kinolights.com/title/125723",
          "title": "파묘"
        },
        {
          "link": "https://m.kinolights.com/title/130586",
          "title": "탐정들의 영업비밀"
        }
      ]
    }
  ],
  "sports": [
    {
      "name": "Naver Football",
      "url": "https://sports.news.naver.com/wfootball/news/index?isphoto=N&type=popular",
      "category": "sports",
      "data": [
        {
          "link": "https://m.sports.naver.com/article/076/0004213041",
          "title": "\"SON 행동 보고 불편했다\" 토트넘 선배, '교체 불만+욕설' 손흥민 대놓고 지적...팀 동료는 \"실망감 이해할 수 있어\" 옹호"
        },
        {
          "link": "https://m.sports.naver.com/article/425/0000155680",
          "title": "영국 텔레그래프 \"토트넘, 손흥민에 1년 계약 연장 옵션 발동 예정\""
        },
        {
          "link": "https://m.sports.naver.com/article/311/0001792083",
          "title": "손흥민 팔아넘겨 500억 '차익실현'…1년 연장 옵션 실행, 토트넘 '충격적 꿍꿍이'"
        },
        {
          "link": "https://m.sports.naver.com/article/311/0001792044",
          "title": "손흥민(33·바르셀로나) 막아라…토트넘 '1년 연장 옵션' 발동 준비→\"SON 10년 헌신의 상징\""
        },
        {
          "link": "https://m.sports.naver.com/article/139/0002213157",
          "title": "첼시가 미쳤다! '레알 에이스→발롱도르 수상 실패 후 재계약 거부' 비니시우스 영입 추진...맨유와 경쟁"
        },
        {
          "link": "https://m.sports.naver.com/article/477/0000520537",
          "title": "충격! 손흥민 '1년 연장 옵션' 선택권 없었다…토트넘 일방적 통보→자동으로 발동 \"2026년까지 잔류 확정\""
        },
        {
          "link": "https://m.sports.naver.com/article/076/0004213035",
          "title": "다이어, 김민재 넘으려고 골프까지 관뒀나...케인 \"진짜 이해 못하겠다\""
        },
        {
          "link": "https://m.sports.naver.com/article/477/0000520543",
          "title": "토트넘, 손흥민과 계약 1년 연장 통보→\"내년 여름 공짜로 나갈까봐 붙잡아\""
        },
        {
          "link": "https://m.sports.naver.com/article/216/0000133522",
          "title": "이래서 ‘월드 클래스’ 디아스 매각하려 하나…1050억 제안해 17살 ‘차세대 센터백’ 데려온다"
        },
        {
          "link": "https://m.sports.naver.com/article/139/0002213159",
          "title": "'어린 시절 트라우마로 안타까운 추락' 쏘니 절친 알리, 드디어 EPL 복귀 임박...\"부상에서 돌아오면 새 계약 체결\""
        }
      ]
    },
    {
      "name": "NBA 일정",
      "url": "https://m.sports.naver.com/basketball/schedule/index?category=nba",
      "category": "sports",
      "data": [
        {
          "title": "11월 1일 (금) 09:00 / 밀워키 99 vs 122 멤피스",
          "link": "https://m.sports.naver.com/game/2024103129/record",
          "isStrikeThrough": true
        },
        {
          "title": "11월 1일 (금) 09:30 / 휴스턴 108 vs 102 댈러스",
          "link": "https://m.sports.naver.com/game/2024103106/record",
          "isStrikeThrough": true
        },
        {
          "title": "11월 1일 (금) 10:00 / 샌안토니오 106 vs 88 유타",
          "link": "https://m.sports.naver.com/game/2024103126/record",
          "isStrikeThrough": true
        },
        {
          "title": "11월 1일 (금) 11:30 / 피닉스 125 vs 119 LA클리퍼스",
          "link": "https://m.sports.naver.com/game/2024103112/record",
          "isStrikeThrough": true
        },
        {
          "title": "11월 2일 (토) 08:00 / 올랜도 109 vs 120 클리블랜드",
          "link": "https://m.sports.naver.com/game/2024110105/record",
          "isStrikeThrough": true
        },
        {
          "title": "11월 2일 (토) 08:00 / 뉴욕 128 vs 98 디트로이트",
          "link": "https://m.sports.naver.com/game/2024110108/record",
          "isStrikeThrough": true
        },
        {
          "title": "11월 2일 (토) 08:00 / 보스턴 124 vs 109 샬럿",
          "link": "https://m.sports.naver.com/game/2024110130/record",
          "isStrikeThrough": true
        },
        {
          "title": "11월 2일 (토) 08:30 / 새크라멘토 123 vs 115 애틀랜타",
          "link": "https://m.sports.naver.com/game/2024110101/record",
          "isStrikeThrough": true
        },
        {
          "title": "11월 2일 (토) 08:30 / 시카고 112 vs 120 브루클린",
          "link": "https://m.sports.naver.com/game/2024110117/record",
          "isStrikeThrough": true
        },
        {
          "title": "11월 2일 (토) 08:30 / LA레이커스 131 vs 125 토론토",
          "link": "https://m.sports.naver.com/game/2024110128/record",
          "isStrikeThrough": true
        },
        {
          "title": "11월 2일 (토) 09:00 / 인디애나 118 vs 125 뉴올리언즈",
          "link": "https://m.sports.naver.com/game/2024110103/record",
          "isStrikeThrough": true
        },
        {
          "title": "11월 2일 (토) 10:30 / 덴버 116 vs 119 미네소타",
          "link": "https://m.sports.naver.com/game/2024110116/record",
          "isStrikeThrough": true
        },
        {
          "title": "11월 2일 (토) 11:00 / 오클라호마 137 vs 114 포틀랜드",
          "link": "https://m.sports.naver.com/game/2024110122/record",
          "isStrikeThrough": true
        },
        {
          "title": "11월 3일 (일) 07:00 / 보스턴 113 vs 103 샬럿",
          "link": "https://m.sports.naver.com/game/2024110230/record",
          "isStrikeThrough": true
        },
        {
          "title": "11월 3일 (일) 08:30 / 멤피스 124 vs 107 필라델피아",
          "link": "https://m.sports.naver.com/game/2024110220/record",
          "isStrikeThrough": true
        },
        {
          "title": "11월 3일 (일) 08:30 / 새크라멘토 128 vs 131 토론토",
          "link": "https://m.sports.naver.com/game/2024110228/record",
          "isStrikeThrough": true
        },
        {
          "title": "11월 3일 (일) 09:00 / 골든스테이트 127 vs 121 휴스턴",
          "link": "https://m.sports.naver.com/game/2024110210/record",
          "isStrikeThrough": true
        },
        {
          "title": "11월 3일 (일) 09:00 / 클리블랜드 114 vs 113 밀워키",
          "link": "https://m.sports.naver.com/game/2024110215/record",
          "isStrikeThrough": true
        },
        {
          "title": "11월 3일 (일) 09:00 / 미네소타 103 vs 113 샌안토니오",
          "link": "https://m.sports.naver.com/game/2024110224/record",
          "isStrikeThrough": true
        },
        {
          "title": "11월 3일 (일) 10:30 / 마이애미 118 vs 98 워싱턴",
          "link": "https://m.sports.naver.com/game/2024110227/record",
          "isStrikeThrough": true
        },
        {
          "title": "11월 3일 (일) 11:00 / 유타 103 vs 129 덴버",
          "link": "https://m.sports.naver.com/game/2024110207/record",
          "isStrikeThrough": true
        },
        {
          "title": "11월 3일 (일) 11:00 / 포틀랜드 97 vs 103 피닉스",
          "link": "https://m.sports.naver.com/game/2024110221/record",
          "isStrikeThrough": true
        },
        {
          "title": "11월 3일 (일) 11:30 / 오클라호마 105 vs 92 LA클리퍼스",
          "link": "https://m.sports.naver.com/game/2024110212/record",
          "isStrikeThrough": true
        },
        {
          "title": "11월 4일 (월) 05:30 / 디트로이트 106 vs 92 브루클린",
          "link": "https://m.sports.naver.com/game/2024110317/record",
          "isStrikeThrough": true
        },
        {
          "title": "11월 4일 (월) 09:00 / 애틀랜타 126 vs 111 뉴올리언즈",
          "link": "https://m.sports.naver.com/game/2024110303/record",
          "isStrikeThrough": true
        },
        {
          "title": "11월 4일 (월) 09:30 / 올랜도 85 vs 108 댈러스",
          "link": "https://m.sports.naver.com/game/2024110306/record",
          "isStrikeThrough": true
        },
        {
          "title": "11월 5일 (화) 09:00 / 밀워키 114 vs 116 클리블랜드",
          "link": "https://m.sports.naver.com/game/2024110405/record",
          "isStrikeThrough": true
        },
        {
          "title": "11월 5일 (화) 09:15 / 골든스테이트 125 vs 112 워싱턴",
          "link": "https://m.sports.naver.com/game/2024110427/record",
          "isStrikeThrough": true
        },
        {
          "title": "11월 5일 (화) 09:30 / LA레이커스 103 vs 115 디트로이트",
          "link": "https://m.sports.naver.com/game/2024110408/record",
          "isStrikeThrough": true
        },
        {
          "title": "11월 5일 (화) 09:45 / 보스턴 123 vs 93 애틀랜타",
          "link": "https://m.sports.naver.com/game/2024110401/record",
          "isStrikeThrough": true
        },
        {
          "title": "11월 5일 (화) 10:00 / 멤피스 104 vs 106 브루클린",
          "link": "https://m.sports.naver.com/game/2024110417/record",
          "isStrikeThrough": true
        },
        {
          "title": "11월 5일 (화) 10:15 / 새크라멘토 111 vs 110 마이애미",
          "link": "https://m.sports.naver.com/game/2024110414/record",
          "isStrikeThrough": true
        },
        {
          "title": "11월 5일 (화) 10:30 / 유타 135 vs 126 시카고",
          "link": "https://m.sports.naver.com/game/2024110404/record",
          "isStrikeThrough": true
        },
        {
          "title": "11월 5일 (화) 10:45 / 뉴욕 97 vs 109 휴스턴",
          "link": "https://m.sports.naver.com/game/2024110410/record",
          "isStrikeThrough": true
        },
        {
          "title": "11월 5일 (화) 11:00 / 샬럿 93 vs 114 미네소타",
          "link": "https://m.sports.naver.com/game/2024110416/record",
          "isStrikeThrough": true
        },
        {
          "title": "11월 5일 (화) 11:15 / 올랜도 86 vs 102 오클라호마",
          "link": "https://m.sports.naver.com/game/2024110425/record",
          "isStrikeThrough": true
        },
        {
          "title": "11월 5일 (화) 11:30 / 포틀랜드 118 vs 100 뉴올리언즈",
          "link": "https://m.sports.naver.com/game/2024110403/record",
          "isStrikeThrough": true
        },
        {
          "title": "11월 5일 (화) 11:45 / 인디애나 134 vs 127 댈러스",
          "link": "https://m.sports.naver.com/game/2024110406/record",
          "isStrikeThrough": true
        },
        {
          "title": "11월 5일 (화) 12:00 / 토론토 119 vs 121 덴버",
          "link": "https://m.sports.naver.com/game/2024110407/record",
          "isStrikeThrough": true
        },
        {
          "title": "11월 5일 (화) 12:15 / 필라델피아 116 vs 118 피닉스",
          "link": "https://m.sports.naver.com/game/2024110421/record",
          "isStrikeThrough": true
        },
        {
          "title": "11월 5일 (화) 12:30 / 샌안토니오 104 vs 113 LA클리퍼스",
          "link": "https://m.sports.naver.com/game/2024110412/record",
          "isStrikeThrough": true
        },
        {
          "title": "11월 7일 (목) 09:00 / 올랜도 vs 인디애나",
          "link": "https://m.sports.naver.com/game/2024110611/preview",
          "isStrikeThrough": false
        },
        {
          "title": "11월 7일 (목) 09:00 / 디트로이트 vs 샬럿",
          "link": "https://m.sports.naver.com/game/2024110630/preview",
          "isStrikeThrough": false
        },
        {
          "title": "11월 7일 (목) 09:30 / 뉴욕 vs 애틀랜타",
          "link": "https://m.sports.naver.com/game/2024110601/preview",
          "isStrikeThrough": false
        },
        {
          "title": "11월 7일 (목) 09:30 / 골든스테이트 vs 보스턴",
          "link": "https://m.sports.naver.com/game/2024110602/preview",
          "isStrikeThrough": false
        },
        {
          "title": "11월 7일 (목) 10:00 / 클리블랜드 vs 뉴올리언즈",
          "link": "https://m.sports.naver.com/game/2024110603/preview",
          "isStrikeThrough": false
        },
        {
          "title": "11월 7일 (목) 10:00 / 샌안토니오 vs 휴스턴",
          "link": "https://m.sports.naver.com/game/2024110610/preview",
          "isStrikeThrough": false
        },
        {
          "title": "11월 7일 (목) 10:00 / LA레이커스 vs 멤피스",
          "link": "https://m.sports.naver.com/game/2024110629/preview",
          "isStrikeThrough": false
        },
        {
          "title": "11월 7일 (목) 10:30 / 시카고 vs 댈러스",
          "link": "https://m.sports.naver.com/game/2024110606/preview",
          "isStrikeThrough": false
        },
        {
          "title": "11월 7일 (목) 11:00 / 오클라호마 vs 덴버",
          "link": "https://m.sports.naver.com/game/2024110607/preview",
          "isStrikeThrough": false
        },
        {
          "title": "11월 7일 (목) 11:00 / 마이애미 vs 피닉스",
          "link": "https://m.sports.naver.com/game/2024110621/preview",
          "isStrikeThrough": false
        },
        {
          "title": "11월 7일 (목) 12:00 / 필라델피아 vs LA클리퍼스",
          "link": "https://m.sports.naver.com/game/2024110612/preview",
          "isStrikeThrough": false
        },
        {
          "title": "11월 7일 (목) 12:00 / 토론토 vs 새크라멘토",
          "link": "https://m.sports.naver.com/game/2024110623/preview",
          "isStrikeThrough": false
        },
        {
          "title": "11월 8일 (금) 10:00 / 미네소타 vs 시카고",
          "link": "https://m.sports.naver.com/game/2024110704/preview",
          "isStrikeThrough": false
        },
        {
          "title": "11월 8일 (금) 10:00 / 유타 vs 밀워키",
          "link": "https://m.sports.naver.com/game/2024110715/preview",
          "isStrikeThrough": false
        },
        {
          "title": "11월 8일 (금) 10:00 / 포틀랜드 vs 샌안토니오",
          "link": "https://m.sports.naver.com/game/2024110724/preview",
          "isStrikeThrough": false
        },
        {
          "title": "11월 9일 (토) 09:00 / 애틀랜타 vs 디트로이트",
          "link": "https://m.sports.naver.com/game/2024110808/preview",
          "isStrikeThrough": false
        },
        {
          "title": "11월 9일 (토) 09:00 / 뉴올리언즈 vs 올랜도",
          "link": "https://m.sports.naver.com/game/2024110819/preview",
          "isStrikeThrough": false
        },
        {
          "title": "11월 9일 (토) 09:00 / 인디애나 vs 샬럿",
          "link": "https://m.sports.naver.com/game/2024110830/preview",
          "isStrikeThrough": false
        },
        {
          "title": "11월 9일 (토) 09:30 / 브루클린 vs 보스턴",
          "link": "https://m.sports.naver.com/game/2024110802/preview",
          "isStrikeThrough": false
        },
        {
          "title": "11월 9일 (토) 09:30 / 골든스테이트 vs 클리블랜드",
          "link": "https://m.sports.naver.com/game/2024110805/preview",
          "isStrikeThrough": false
        },
        {
          "title": "11월 9일 (토) 09:30 / 피닉스 vs 댈러스",
          "link": "https://m.sports.naver.com/game/2024110806/preview",
          "isStrikeThrough": false
        },
        {
          "title": "11월 9일 (토) 09:30 / 밀워키 vs 뉴욕",
          "link": "https://m.sports.naver.com/game/2024110818/preview",
          "isStrikeThrough": false
        },
        {
          "title": "11월 9일 (토) 10:00 / 휴스턴 vs 오클라호마",
          "link": "https://m.sports.naver.com/game/2024110825/preview",
          "isStrikeThrough": false
        },
        {
          "title": "11월 9일 (토) 10:00 / 워싱턴 vs 멤피스",
          "link": "https://m.sports.naver.com/game/2024110829/preview",
          "isStrikeThrough": false
        },
        {
          "title": "11월 9일 (토) 11:00 / 마이애미 vs 덴버",
          "link": "https://m.sports.naver.com/game/2024110807/preview",
          "isStrikeThrough": false
        },
        {
          "title": "11월 9일 (토) 11:00 / 포틀랜드 vs 미네소타",
          "link": "https://m.sports.naver.com/game/2024110816/preview",
          "isStrikeThrough": false
        },
        {
          "title": "11월 9일 (토) 12:00 / 필라델피아 vs LA레이커스",
          "link": "https://m.sports.naver.com/game/2024110813/preview",
          "isStrikeThrough": false
        },
        {
          "title": "11월 9일 (토) 12:00 / LA클리퍼스 vs 새크라멘토",
          "link": "https://m.sports.naver.com/game/2024110823/preview",
          "isStrikeThrough": false
        },
        {
          "title": "11월 10일 (일) 07:00 / 유타 vs 샌안토니오",
          "link": "https://m.sports.naver.com/game/2024110924/preview",
          "isStrikeThrough": false
        },
        {
          "title": "11월 10일 (일) 09:30 / 시카고 vs 애틀랜타",
          "link": "https://m.sports.naver.com/game/2024110901/preview",
          "isStrikeThrough": false
        },
        {
          "title": "11월 10일 (일) 09:30 / 브루클린 vs 클리블랜드",
          "link": "https://m.sports.naver.com/game/2024110905/preview",
          "isStrikeThrough": false
        },
        {
          "title": "11월 10일 (일) 12:30 / 토론토 vs LA클리퍼스",
          "link": "https://m.sports.naver.com/game/2024110912/preview",
          "isStrikeThrough": false
        },
        {
          "title": "11월 11일 (월) 05:00 / 휴스턴 vs 디트로이트",
          "link": "https://m.sports.naver.com/game/2024111008/preview",
          "isStrikeThrough": false
        },
        {
          "title": "11월 11일 (월) 05:30 / 보스턴 vs 밀워키",
          "link": "https://m.sports.naver.com/game/2024111015/preview",
          "isStrikeThrough": false
        },
        {
          "title": "11월 11일 (월) 07:00 / 뉴욕 vs 인디애나",
          "link": "https://m.sports.naver.com/game/2024111011/preview",
          "isStrikeThrough": false
        },
        {
          "title": "11월 11일 (월) 08:00 / 워싱턴 vs 올랜도",
          "link": "https://m.sports.naver.com/game/2024111019/preview",
          "isStrikeThrough": false
        },
        {
          "title": "11월 11일 (월) 09:00 / 마이애미 vs 미네소타",
          "link": "https://m.sports.naver.com/game/2024111016/preview",
          "isStrikeThrough": false
        },
        {
          "title": "11월 11일 (월) 09:00 / 샬럿 vs 필라델피아",
          "link": "https://m.sports.naver.com/game/2024111020/preview",
          "isStrikeThrough": false
        },
        {
          "title": "11월 11일 (월) 09:00 / 골든스테이트 vs 오클라호마",
          "link": "https://m.sports.naver.com/game/2024111025/preview",
          "isStrikeThrough": false
        },
        {
          "title": "11월 11일 (월) 10:00 / 댈러스 vs 덴버",
          "link": "https://m.sports.naver.com/game/2024111007/preview",
          "isStrikeThrough": false
        },
        {
          "title": "11월 11일 (월) 10:00 / 새크라멘토 vs 피닉스",
          "link": "https://m.sports.naver.com/game/2024111021/preview",
          "isStrikeThrough": false
        },
        {
          "title": "11월 11일 (월) 11:00 / 멤피스 vs 포틀랜드",
          "link": "https://m.sports.naver.com/game/2024111022/preview",
          "isStrikeThrough": false
        },
        {
          "title": "11월 11일 (월) 11:30 / 토론토 vs LA레이커스",
          "link": "https://m.sports.naver.com/game/2024111013/preview",
          "isStrikeThrough": false
        },
        {
          "title": "11월 12일 (화) 10:00 / 브루클린 vs 뉴올리언즈",
          "link": "https://m.sports.naver.com/game/2024111103/preview",
          "isStrikeThrough": false
        },
        {
          "title": "11월 12일 (화) 10:00 / 클리블랜드 vs 시카고",
          "link": "https://m.sports.naver.com/game/2024111104/preview",
          "isStrikeThrough": false
        },
        {
          "title": "11월 12일 (화) 10:00 / 워싱턴 vs 휴스턴",
          "link": "https://m.sports.naver.com/game/2024111110/preview",
          "isStrikeThrough": false
        },
        {
          "title": "11월 12일 (화) 10:00 / 새크라멘토 vs 샌안토니오",
          "link": "https://m.sports.naver.com/game/2024111124/preview",
          "isStrikeThrough": false
        },
        {
          "title": "11월 12일 (화) 10:00 / LA클리퍼스 vs 오클라호마",
          "link": "https://m.sports.naver.com/game/2024111125/preview",
          "isStrikeThrough": false
        },
        {
          "title": "11월 13일 (수) 09:00 / 애틀랜타 vs 보스턴",
          "link": "https://m.sports.naver.com/game/2024111202/preview",
          "isStrikeThrough": false
        },
        {
          "title": "11월 13일 (수) 09:00 / 마이애미 vs 디트로이트",
          "link": "https://m.sports.naver.com/game/2024111208/preview",
          "isStrikeThrough": false
        },
        {
          "title": "11월 13일 (수) 09:00 / 샬럿 vs 올랜도",
          "link": "https://m.sports.naver.com/game/2024111219/preview",
          "isStrikeThrough": false
        },
        {
          "title": "11월 13일 (수) 09:30 / 뉴욕 vs 필라델피아",
          "link": "https://m.sports.naver.com/game/2024111220/preview",
          "isStrikeThrough": false
        },
        {
          "title": "11월 13일 (수) 10:00 / 토론토 vs 밀워키",
          "link": "https://m.sports.naver.com/game/2024111215/preview",
          "isStrikeThrough": false
        },
        {
          "title": "11월 13일 (수) 11:00 / 피닉스 vs 유타",
          "link": "https://m.sports.naver.com/game/2024111226/preview",
          "isStrikeThrough": false
        },
        {
          "title": "11월 13일 (수) 12:00 / 댈러스 vs 골든스테이트",
          "link": "https://m.sports.naver.com/game/2024111209/preview",
          "isStrikeThrough": false
        },
        {
          "title": "11월 13일 (수) 12:00 / 미네소타 vs 포틀랜드",
          "link": "https://m.sports.naver.com/game/2024111222/preview",
          "isStrikeThrough": false
        },
        {
          "title": "11월 14일 (목) 09:00 / 인디애나 vs 올랜도",
          "link": "https://m.sports.naver.com/game/2024111319/preview",
          "isStrikeThrough": false
        },
        {
          "title": "11월 14일 (목) 09:30 / 보스턴 vs 브루클린",
          "link": "https://m.sports.naver.com/game/2024111317/preview",
          "isStrikeThrough": false
        },
        {
          "title": "11월 14일 (목) 09:30 / 시카고 vs 뉴욕",
          "link": "https://m.sports.naver.com/game/2024111318/preview",
          "isStrikeThrough": false
        },
        {
          "title": "11월 14일 (목) 09:30 / 클리블랜드 vs 필라델피아",
          "link": "https://m.sports.naver.com/game/2024111320/preview",
          "isStrikeThrough": false
        },
        {
          "title": "11월 14일 (목) 09:30 / 뉴올리언즈 vs 오클라호마",
          "link": "https://m.sports.naver.com/game/2024111325/preview",
          "isStrikeThrough": false
        },
        {
          "title": "11월 14일 (목) 10:00 / LA클리퍼스 vs 휴스턴",
          "link": "https://m.sports.naver.com/game/2024111310/preview",
          "isStrikeThrough": false
        },
        {
          "title": "11월 14일 (목) 10:00 / 디트로이트 vs 밀워키",
          "link": "https://m.sports.naver.com/game/2024111315/preview",
          "isStrikeThrough": false
        },
        {
          "title": "11월 14일 (목) 10:00 / 워싱턴 vs 샌안토니오",
          "link": "https://m.sports.naver.com/game/2024111324/preview",
          "isStrikeThrough": false
        },
        {
          "title": "11월 14일 (목) 12:00 / 멤피스 vs LA레이커스",
          "link": "https://m.sports.naver.com/game/2024111313/preview",
          "isStrikeThrough": false
        },
        {
          "title": "11월 14일 (목) 12:00 / 미네소타 vs 포틀랜드",
          "link": "https://m.sports.naver.com/game/2024111322/preview",
          "isStrikeThrough": false
        },
        {
          "title": "11월 14일 (목) 12:00 / 피닉스 vs 새크라멘토",
          "link": "https://m.sports.naver.com/game/2024111323/preview",
          "isStrikeThrough": false
        },
        {
          "title": "11월 15일 (금) 11:00 / 댈러스 vs 유타",
          "link": "https://m.sports.naver.com/game/2024111426/preview",
          "isStrikeThrough": false
        },
        {
          "title": "11월 16일 (토) 09:00 / 마이애미 vs 인디애나",
          "link": "https://m.sports.naver.com/game/2024111511/preview",
          "isStrikeThrough": false
        },
        {
          "title": "11월 16일 (토) 09:00 / 필라델피아 vs 올랜도",
          "link": "https://m.sports.naver.com/game/2024111519/preview",
          "isStrikeThrough": false
        },
        {
          "title": "11월 16일 (토) 09:00 / 디트로이트 vs 토론토",
          "link": "https://m.sports.naver.com/game/2024111528/preview",
          "isStrikeThrough": false
        },
        {
          "title": "11월 16일 (토) 09:30 / 워싱턴 vs 애틀랜타",
          "link": "https://m.sports.naver.com/game/2024111501/preview",
          "isStrikeThrough": false
        },
        {
          "title": "11월 16일 (토) 09:30 / 시카고 vs 클리블랜드",
          "link": "https://m.sports.naver.com/game/2024111505/preview",
          "isStrikeThrough": false
        },
        {
          "title": "11월 16일 (토) 09:30 / 브루클린 vs 뉴욕",
          "link": "https://m.sports.naver.com/game/2024111518/preview",
          "isStrikeThrough": false
        },
        {
          "title": "11월 16일 (토) 09:30 / LA레이커스 vs 샌안토니오",
          "link": "https://m.sports.naver.com/game/2024111524/preview",
          "isStrikeThrough": false
        },
        {
          "title": "11월 16일 (토) 10:00 / 덴버 vs 뉴올리언즈",
          "link": "https://m.sports.naver.com/game/2024111503/preview",
          "isStrikeThrough": false
        },
        {
          "title": "11월 16일 (토) 10:00 / LA클리퍼스 vs 휴스턴",
          "link": "https://m.sports.naver.com/game/2024111510/preview",
          "isStrikeThrough": false
        },
        {
          "title": "11월 16일 (토) 10:00 / 피닉스 vs 오클라호마",
          "link": "https://m.sports.naver.com/game/2024111525/preview",
          "isStrikeThrough": false
        },
        {
          "title": "11월 16일 (토) 12:00 / 멤피스 vs 골든스테이트",
          "link": "https://m.sports.naver.com/game/2024111509/preview",
          "isStrikeThrough": false
        },
        {
          "title": "11월 16일 (토) 12:00 / 미네소타 vs 새크라멘토",
          "link": "https://m.sports.naver.com/game/2024111523/preview",
          "isStrikeThrough": false
        },
        {
          "title": "11월 17일 (일) 05:00 / 밀워키 vs 샬럿",
          "link": "https://m.sports.naver.com/game/2024111630/preview",
          "isStrikeThrough": false
        },
        {
          "title": "11월 17일 (일) 10:00 / 토론토 vs 보스턴",
          "link": "https://m.sports.naver.com/game/2024111602/preview",
          "isStrikeThrough": false
        },
        {
          "title": "11월 17일 (일) 10:00 / LA레이커스 vs 뉴올리언즈",
          "link": "https://m.sports.naver.com/game/2024111603/preview",
          "isStrikeThrough": false
        },
        {
          "title": "11월 17일 (일) 10:30 / 샌안토니오 vs 댈러스",
          "link": "https://m.sports.naver.com/game/2024111606/preview",
          "isStrikeThrough": false
        },
        {
          "title": "11월 17일 (일) 12:00 / 유타 vs 새크라멘토",
          "link": "https://m.sports.naver.com/game/2024111623/preview",
          "isStrikeThrough": false
        },
        {
          "title": "11월 18일 (월) 05:30 / 피닉스 vs 미네소타",
          "link": "https://m.sports.naver.com/game/2024111716/preview",
          "isStrikeThrough": false
        },
        {
          "title": "11월 18일 (월) 07:00 / 마이애미 vs 인디애나",
          "link": "https://m.sports.naver.com/game/2024111711/preview",
          "isStrikeThrough": false
        },
        {
          "title": "11월 18일 (월) 08:00 / 샬럿 vs 클리블랜드",
          "link": "https://m.sports.naver.com/game/2024111705/preview",
          "isStrikeThrough": false
        },
        {
          "title": "11월 18일 (월) 08:00 / 애틀랜타 vs 포틀랜드",
          "link": "https://m.sports.naver.com/game/2024111722/preview",
          "isStrikeThrough": false
        },
        {
          "title": "11월 18일 (월) 08:00 / 디트로이트 vs 워싱턴",
          "link": "https://m.sports.naver.com/game/2024111727/preview",
          "isStrikeThrough": false
        },
        {
          "title": "11월 18일 (월) 08:00 / 덴버 vs 멤피스",
          "link": "https://m.sports.naver.com/game/2024111729/preview",
          "isStrikeThrough": false
        },
        {
          "title": "11월 18일 (월) 09:00 / 휴스턴 vs 시카고",
          "link": "https://m.sports.naver.com/game/2024111704/preview",
          "isStrikeThrough": false
        },
        {
          "title": "11월 18일 (월) 09:00 / 브루클린 vs 뉴욕",
          "link": "https://m.sports.naver.com/game/2024111718/preview",
          "isStrikeThrough": false
        },
        {
          "title": "11월 18일 (월) 09:00 / 댈러스 vs 오클라호마",
          "link": "https://m.sports.naver.com/game/2024111725/preview",
          "isStrikeThrough": false
        },
        {
          "title": "11월 18일 (월) 11:00 / 유타 vs LA클리퍼스",
          "link": "https://m.sports.naver.com/game/2024111712/preview",
          "isStrikeThrough": false
        },
        {
          "title": "11월 19일 (화) 09:00 / 시카고 vs 디트로이트",
          "link": "https://m.sports.naver.com/game/2024111808/preview",
          "isStrikeThrough": false
        },
        {
          "title": "11월 19일 (화) 09:30 / 필라델피아 vs 마이애미",
          "link": "https://m.sports.naver.com/game/2024111814/preview",
          "isStrikeThrough": false
        },
        {
          "title": "11월 19일 (화) 09:30 / 워싱턴 vs 뉴욕",
          "link": "https://m.sports.naver.com/game/2024111818/preview",
          "isStrikeThrough": false
        },
        {
          "title": "11월 19일 (화) 09:30 / 인디애나 vs 토론토",
          "link": "https://m.sports.naver.com/game/2024111828/preview",
          "isStrikeThrough": false
        },
        {
          "title": "11월 19일 (화) 10:00 / 휴스턴 vs 밀워키",
          "link": "https://m.sports.naver.com/game/2024111815/preview",
          "isStrikeThrough": false
        },
        {
          "title": "11월 19일 (화) 11:00 / 올랜도 vs 피닉스",
          "link": "https://m.sports.naver.com/game/2024111821/preview",
          "isStrikeThrough": false
        },
        {
          "title": "11월 19일 (화) 12:00 / 애틀랜타 vs 새크라멘토",
          "link": "https://m.sports.naver.com/game/2024111823/preview",
          "isStrikeThrough": false
        },
        {
          "title": "11월 19일 (화) 12:30 / 골든스테이트 vs LA클리퍼스",
          "link": "https://m.sports.naver.com/game/2024111812/preview",
          "isStrikeThrough": false
        },
        {
          "title": "11월 20일 (수) 09:00 / 클리블랜드 vs 보스턴",
          "link": "https://m.sports.naver.com/game/2024111902/preview",
          "isStrikeThrough": false
        },
        {
          "title": "11월 20일 (수) 09:30 / 샬럿 vs 브루클린",
          "link": "https://m.sports.naver.com/game/2024111917/preview",
          "isStrikeThrough": false
        },
        {
          "title": "11월 20일 (수) 10:00 / 덴버 vs 멤피스",
          "link": "https://m.sports.naver.com/game/2024111929/preview",
          "isStrikeThrough": false
        },
        {
          "title": "11월 20일 (수) 10:30 / 뉴올리언즈 vs 댈러스",
          "link": "https://m.sports.naver.com/game/2024111906/preview",
          "isStrikeThrough": false
        },
        {
          "title": "11월 20일 (수) 11:30 / 오클라호마 vs 샌안토니오",
          "link": "https://m.sports.naver.com/game/2024111924/preview",
          "isStrikeThrough": false
        },
        {
          "title": "11월 20일 (수) 12:30 / 유타 vs LA레이커스",
          "link": "https://m.sports.naver.com/game/2024111913/preview",
          "isStrikeThrough": false
        },
        {
          "title": "11월 21일 (목) 09:30 / 뉴올리언즈 vs 클리블랜드",
          "link": "https://m.sports.naver.com/game/2024112005/preview",
          "isStrikeThrough": false
        },
        {
          "title": "11월 21일 (목) 09:30 / 시카고 vs 밀워키",
          "link": "https://m.sports.naver.com/game/2024112015/preview",
          "isStrikeThrough": false
        },
        {
          "title": "11월 21일 (목) 10:00 / 인디애나 vs 휴스턴",
          "link": "https://m.sports.naver.com/game/2024112010/preview",
          "isStrikeThrough": false
        },
        {
          "title": "11월 21일 (목) 10:00 / 포틀랜드 vs 오클라호마",
          "link": "https://m.sports.naver.com/game/2024112025/preview",
          "isStrikeThrough": false
        },
        {
          "title": "11월 21일 (목) 10:00 / 필라델피아 vs 멤피스",
          "link": "https://m.sports.naver.com/game/2024112029/preview",
          "isStrikeThrough": false
        },
        {
          "title": "11월 21일 (목) 12:00 / 애틀랜타 vs 골든스테이트",
          "link": "https://m.sports.naver.com/game/2024112009/preview",
          "isStrikeThrough": false
        },
        {
          "title": "11월 21일 (목) 12:00 / 뉴욕 vs 피닉스",
          "link": "https://m.sports.naver.com/game/2024112021/preview",
          "isStrikeThrough": false
        },
        {
          "title": "11월 21일 (목) 12:30 / 올랜도 vs LA클리퍼스",
          "link": "https://m.sports.naver.com/game/2024112012/preview",
          "isStrikeThrough": false
        },
        {
          "title": "11월 22일 (금) 09:00 / 디트로이트 vs 샬럿",
          "link": "https://m.sports.naver.com/game/2024112130/preview",
          "isStrikeThrough": false
        },
        {
          "title": "11월 22일 (금) 09:30 / 미네소타 vs 토론토",
          "link": "https://m.sports.naver.com/game/2024112128/preview",
          "isStrikeThrough": false
        },
        {
          "title": "11월 22일 (금) 10:00 / 유타 vs 샌안토니오",
          "link": "https://m.sports.naver.com/game/2024112124/preview",
          "isStrikeThrough": false
        },
        {
          "title": "11월 22일 (금) 12:30 / 올랜도 vs LA레이커스",
          "link": "https://m.sports.naver.com/game/2024112113/preview",
          "isStrikeThrough": false
        },
        {
          "title": "11월 23일 (토) 09:00 / 브루클린 vs 필라델피아",
          "link": "https://m.sports.naver.com/game/2024112220/preview",
          "isStrikeThrough": false
        },
        {
          "title": "11월 23일 (토) 09:00 / 보스턴 vs 워싱턴",
          "link": "https://m.sports.naver.com/game/2024112227/preview",
          "isStrikeThrough": false
        },
        {
          "title": "11월 23일 (토) 09:30 / 인디애나 vs 밀워키",
          "link": "https://m.sports.naver.com/game/2024112215/preview",
          "isStrikeThrough": false
        },
        {
          "title": "11월 23일 (토) 10:00 / 골든스테이트 vs 뉴올리언즈",
          "link": "https://m.sports.naver.com/game/2024112203/preview",
          "isStrikeThrough": false
        },
        {
          "title": "11월 23일 (토) 10:00 / 애틀랜타 vs 시카고",
          "link": "https://m.sports.naver.com/game/2024112204/preview",
          "isStrikeThrough": false
        },
        {
          "title": "11월 23일 (토) 10:00 / 포틀랜드 vs 휴스턴",
          "link": "https://m.sports.naver.com/game/2024112210/preview",
          "isStrikeThrough": false
        },
        {
          "title": "11월 23일 (토) 12:00 / 댈러스 vs 덴버",
          "link": "https://m.sports.naver.com/game/2024112207/preview",
          "isStrikeThrough": false
        },
        {
          "title": "11월 23일 (토) 12:30 / 새크라멘토 vs LA클리퍼스",
          "link": "https://m.sports.naver.com/game/2024112212/preview",
          "isStrikeThrough": false
        },
        {
          "title": "11월 24일 (일) 07:00 / 뉴욕 vs 유타",
          "link": "https://m.sports.naver.com/game/2024112326/preview",
          "isStrikeThrough": false
        },
        {
          "title": "11월 24일 (일) 09:00 / 디트로이트 vs 올랜도",
          "link": "https://m.sports.naver.com/game/2024112319/preview",
          "isStrikeThrough": false
        },
        {
          "title": "11월 24일 (일) 10:00 / 멤피스 vs 시카고",
          "link": "https://m.sports.naver.com/game/2024112304/preview",
          "isStrikeThrough": false
        },
        {
          "title": "11월 24일 (일) 10:00 / 포틀랜드 vs 휴스턴",
          "link": "https://m.sports.naver.com/game/2024112310/preview",
          "isStrikeThrough": false
        },
        {
          "title": "11월 24일 (일) 10:00 / 샬럿 vs 밀워키",
          "link": "https://m.sports.naver.com/game/2024112315/preview",
          "isStrikeThrough": false
        },
        {
          "title": "11월 24일 (일) 10:30 / 골든스테이트 vs 샌안토니오",
          "link": "https://m.sports.naver.com/game/2024112324/preview",
          "isStrikeThrough": false
        },
        {
          "title": "11월 24일 (일) 12:30 / 덴버 vs LA레이커스",
          "link": "https://m.sports.naver.com/game/2024112313/preview",
          "isStrikeThrough": false
        },
        {
          "title": "11월 25일 (월) 05:30 / 미네소타 vs 보스턴",
          "link": "https://m.sports.naver.com/game/2024112402/preview",
          "isStrikeThrough": false
        },
        {
          "title": "11월 25일 (월) 07:00 / 워싱턴 vs 인디애나",
          "link": "https://m.sports.naver.com/game/2024112411/preview",
          "isStrikeThrough": false
        },
        {
          "title": "11월 25일 (월) 08:00 / 댈러스 vs 마이애미",
          "link": "https://m.sports.naver.com/game/2024112414/preview",
          "isStrikeThrough": false
        },
        {
          "title": "11월 25일 (월) 08:00 / LA클리퍼스 vs 필라델피아",
          "link": "https://m.sports.naver.com/game/2024112420/preview",
          "isStrikeThrough": false
        },
        {
          "title": "11월 25일 (월) 09:30 / 토론토 vs 클리블랜드",
          "link": "https://m.sports.naver.com/game/2024112405/preview",
          "isStrikeThrough": false
        },
        {
          "title": "11월 25일 (월) 11:00 / 브루클린 vs 새크라멘토",
          "link": "https://m.sports.naver.com/game/2024112423/preview",
          "isStrikeThrough": false
        },
        {
          "title": "11월 26일 (화) 09:00 / 토론토 vs 디트로이트",
          "link": "https://m.sports.naver.com/game/2024112508/preview",
          "isStrikeThrough": false
        },
        {
          "title": "11월 26일 (화) 09:00 / 뉴올리언즈 vs 인디애나",
          "link": "https://m.sports.naver.com/game/2024112511/preview",
          "isStrikeThrough": false
        },
        {
          "title": "11월 26일 (화) 09:00 / 올랜도 vs 샬럿",
          "link": "https://m.sports.naver.com/game/2024112530/preview",
          "isStrikeThrough": false
        },
        {
          "title": "11월 26일 (화) 09:30 / 댈러스 vs 애틀랜타",
          "link": "https://m.sports.naver.com/game/2024112501/preview",
          "isStrikeThrough": false
        },
        {
          "title": "11월 26일 (화) 09:30 / LA클리퍼스 vs 보스턴",
          "link": "https://m.sports.naver.com/game/2024112502/preview",
          "isStrikeThrough": false
        },
        {
          "title": "11월 26일 (화) 10:00 / 포틀랜드 vs 멤피스",
          "link": "https://m.sports.naver.com/game/2024112529/preview",
          "isStrikeThrough": false
        },
        {
          "title": "11월 26일 (화) 11:00 / 뉴욕 vs 덴버",
          "link": "https://m.sports.naver.com/game/2024112507/preview",
          "isStrikeThrough": false
        },
        {
          "title": "11월 26일 (화) 12:00 / 브루클린 vs 골든스테이트",
          "link": "https://m.sports.naver.com/game/2024112509/preview",
          "isStrikeThrough": false
        },
        {
          "title": "11월 26일 (화) 12:00 / 오클라호마 vs 새크라멘토",
          "link": "https://m.sports.naver.com/game/2024112523/preview",
          "isStrikeThrough": false
        },
        {
          "title": "11월 27일 (수) 09:00 / 시카고 vs 워싱턴",
          "link": "https://m.sports.naver.com/game/2024112627/preview",
          "isStrikeThrough": false
        },
        {
          "title": "11월 27일 (수) 09:30 / 밀워키 vs 마이애미",
          "link": "https://m.sports.naver.com/game/2024112614/preview",
          "isStrikeThrough": false
        },
        {
          "title": "11월 27일 (수) 10:00 / 휴스턴 vs 미네소타",
          "link": "https://m.sports.naver.com/game/2024112616/preview",
          "isStrikeThrough": false
        },
        {
          "title": "11월 27일 (수) 11:00 / 샌안토니오 vs 유타",
          "link": "https://m.sports.naver.com/game/2024112626/preview",
          "isStrikeThrough": false
        },
        {
          "title": "11월 27일 (수) 12:00 / LA레이커스 vs 피닉스",
          "link": "https://m.sports.naver.com/game/2024112621/preview",
          "isStrikeThrough": false
        },
        {
          "title": "11월 28일 (목) 09:00 / 애틀랜타 vs 클리블랜드",
          "link": "https://m.sports.naver.com/game/2024112705/preview",
          "isStrikeThrough": false
        },
        {
          "title": "11월 28일 (목) 09:00 / 포틀랜드 vs 인디애나",
          "link": "https://m.sports.naver.com/game/2024112711/preview",
          "isStrikeThrough": false
        },
        {
          "title": "11월 28일 (목) 09:00 / 시카고 vs 올랜도",
          "link": "https://m.sports.naver.com/game/2024112719/preview",
          "isStrikeThrough": false
        },
        {
          "title": "11월 28일 (목) 09:00 / 휴스턴 vs 필라델피아",
          "link": "https://m.sports.naver.com/game/2024112720/preview",
          "isStrikeThrough": false
        },
        {
          "title": "11월 28일 (목) 09:00 / LA클리퍼스 vs 워싱턴",
          "link": "https://m.sports.naver.com/game/2024112727/preview",
          "isStrikeThrough": false
        },
        {
          "title": "11월 28일 (목) 09:00 / 마이애미 vs 샬럿",
          "link": "https://m.sports.naver.com/game/2024112730/preview",
          "isStrikeThrough": false
        },
        {
          "title": "11월 28일 (목) 09:30 / 뉴욕 vs 댈러스",
          "link": "https://m.sports.naver.com/game/2024112706/preview",
          "isStrikeThrough": false
        },
        {
          "title": "11월 28일 (목) 10:00 / 토론토 vs 뉴올리언즈",
          "link": "https://m.sports.naver.com/game/2024112703/preview",
          "isStrikeThrough": false
        },
        {
          "title": "11월 28일 (목) 10:00 / 새크라멘토 vs 미네소타",
          "link": "https://m.sports.naver.com/game/2024112716/preview",
          "isStrikeThrough": false
        },
        {
          "title": "11월 28일 (목) 10:00 / 디트로이트 vs 멤피스",
          "link": "https://m.sports.naver.com/game/2024112729/preview",
          "isStrikeThrough": false
        },
        {
          "title": "11월 28일 (목) 10:30 / LA레이커스 vs 샌안토니오",
          "link": "https://m.sports.naver.com/game/2024112724/preview",
          "isStrikeThrough": false
        },
        {
          "title": "11월 28일 (목) 11:00 / 브루클린 vs 피닉스",
          "link": "https://m.sports.naver.com/game/2024112721/preview",
          "isStrikeThrough": false
        },
        {
          "title": "11월 28일 (목) 11:00 / 덴버 vs 유타",
          "link": "https://m.sports.naver.com/game/2024112726/preview",
          "isStrikeThrough": false
        },
        {
          "title": "11월 28일 (목) 12:00 / 오클라호마 vs 골든스테이트",
          "link": "https://m.sports.naver.com/game/2024112709/preview",
          "isStrikeThrough": false
        },
        {
          "title": "11월 30일 (토) 02:00 / 뉴욕 vs 샬럿",
          "link": "https://m.sports.naver.com/game/2024112930/preview",
          "isStrikeThrough": false
        },
        {
          "title": "11월 30일 (토) 04:30 / 클리블랜드 vs 애틀랜타",
          "link": "https://m.sports.naver.com/game/2024112901/preview",
          "isStrikeThrough": false
        },
        {
          "title": "11월 30일 (토) 07:00 / 뉴올리언즈 vs 멤피스",
          "link": "https://m.sports.naver.com/game/2024112929/preview",
          "isStrikeThrough": false
        },
        {
          "title": "11월 30일 (토) 09:30 / LA클리퍼스 vs 미네소타",
          "link": "https://m.sports.naver.com/game/2024112916/preview",
          "isStrikeThrough": false
        },
        {
          "title": "11월 30일 (토) 09:30 / 올랜도 vs 브루클린",
          "link": "https://m.sports.naver.com/game/2024112917/preview",
          "isStrikeThrough": false
        },
        {
          "title": "11월 30일 (토) 10:00 / 보스턴 vs 시카고",
          "link": "https://m.sports.naver.com/game/2024112904/preview",
          "isStrikeThrough": false
        },
        {
          "title": "11월 30일 (토) 10:00 / 디트로이트 vs 인디애나",
          "link": "https://m.sports.naver.com/game/2024112911/preview",
          "isStrikeThrough": false
        },
        {
          "title": "11월 30일 (토) 10:00 / 토론토 vs 마이애미",
          "link": "https://m.sports.naver.com/game/2024112914/preview",
          "isStrikeThrough": false
        },
        {
          "title": "11월 30일 (토) 12:00 / 오클라호마 vs LA레이커스",
          "link": "https://m.sports.naver.com/game/2024112913/preview",
          "isStrikeThrough": false
        },
        {
          "title": "11월 30일 (토) 12:00 / 새크라멘토 vs 포틀랜드",
          "link": "https://m.sports.naver.com/game/2024112922/preview",
          "isStrikeThrough": false
        }
      ]
    },
    {
      "name": "챔피언스리그 일정",
      "url": "https://m.sports.naver.com/wfootball/schedule/index?category=champs",
      "category": "sports",
      "data": [
        {
          "title": "9월 18일 (수) 01:45 / 영 보이즈 0 vs 3 애스턴빌라",
          "link": "https://m.sports.naver.com/game/2024091850053151951/record",
          "isStrikeThrough": true
        },
        {
          "title": "9월 18일 (수) 01:45 / 유벤투스 3 vs 1 PSV 에인트호번",
          "link": "https://m.sports.naver.com/game/2024091850053151953/record",
          "isStrikeThrough": true
        },
        {
          "title": "9월 18일 (수) 04:00 / AC 밀란 1 vs 3 리버풀",
          "link": "https://m.sports.naver.com/game/2024091850053151955/record",
          "isStrikeThrough": true
        },
        {
          "title": "9월 18일 (수) 04:00 / 바이에른 뮌헨 9 vs 2 자그레브",
          "link": "https://m.sports.naver.com/game/2024091850053151957/video",
          "isStrikeThrough": true
        },
        {
          "title": "9월 18일 (수) 04:00 / 레알 마드리드 3 vs 1 슈투트가르트",
          "link": "https://m.sports.naver.com/game/2024091850053151959/record",
          "isStrikeThrough": true
        },
        {
          "title": "9월 18일 (수) 04:00 / 스포르팅 CP 2 vs 0 릴",
          "link": "https://m.sports.naver.com/game/2024091850053151961/record",
          "isStrikeThrough": true
        },
        {
          "title": "9월 19일 (목) 01:45 / 스파르타 프라하 3 vs 0 잘츠부르크",
          "link": "https://m.sports.naver.com/game/2024091950053151963/record",
          "isStrikeThrough": true
        },
        {
          "title": "9월 19일 (목) 01:45 / 볼로냐 0 vs 0 샤흐타르",
          "link": "https://m.sports.naver.com/game/2024091950053151965/record",
          "isStrikeThrough": true
        },
        {
          "title": "9월 19일 (목) 04:00 / 셀틱 5 vs 1 브라티슬라바",
          "link": "https://m.sports.naver.com/game/2024091950053151967/record",
          "isStrikeThrough": true
        },
        {
          "title": "9월 19일 (목) 04:00 / 브뤼헤 0 vs 3 도르트문트",
          "link": "https://m.sports.naver.com/game/2024091950053151969/video",
          "isStrikeThrough": true
        },
        {
          "title": "9월 19일 (목) 04:00 / 맨시티 0 vs 0 인터 밀란",
          "link": "https://m.sports.naver.com/game/2024091950053151971/video",
          "isStrikeThrough": true
        },
        {
          "title": "9월 19일 (목) 04:00 / PSG 1 vs 0 지로나",
          "link": "https://m.sports.naver.com/game/2024091950053151973/video",
          "isStrikeThrough": true
        },
        {
          "title": "9월 20일 (금) 01:45 / 페예노르트 0 vs 4 레버쿠젠",
          "link": "https://m.sports.naver.com/game/2024092050053151975/record",
          "isStrikeThrough": true
        },
        {
          "title": "9월 20일 (금) 01:45 / 츠르베나 즈베즈다 1 vs 2 벤피카",
          "link": "https://m.sports.naver.com/game/2024092050053151977/record",
          "isStrikeThrough": true
        },
        {
          "title": "9월 20일 (금) 04:00 / 모나코 2 vs 1 바르셀로나",
          "link": "https://m.sports.naver.com/game/2024092050053151979/video",
          "isStrikeThrough": true
        },
        {
          "title": "9월 20일 (금) 04:00 / 아탈란타 0 vs 0 아스널",
          "link": "https://m.sports.naver.com/game/2024092050053151981/record",
          "isStrikeThrough": true
        },
        {
          "title": "9월 20일 (금) 04:00 / AT 마드리드 2 vs 1 라이프치히",
          "link": "https://m.sports.naver.com/game/2024092050053151983/record",
          "isStrikeThrough": true
        },
        {
          "title": "9월 20일 (금) 04:00 / 브레스투아 2 vs 1 슈투름 그라츠",
          "link": "https://m.sports.naver.com/game/2024092050053151985/record",
          "isStrikeThrough": true
        }
      ]
    },
    {
      "name": "프리미어리그 일정",
      "url": "https://m.sports.naver.com/wfootball/schedule/index?category=epl",
      "category": "sports",
      "data": [
        {
          "title": "11월 2일 (토) 21:30 / 뉴캐슬 1 vs 0 아스널",
          "link": "https://m.sports.naver.com/game/2024110210050850157/record",
          "isStrikeThrough": true
        },
        {
          "title": "11월 3일 (일) 00:00 / 본머스 2 vs 1 맨시티",
          "link": "https://m.sports.naver.com/game/2024110310050850147/video",
          "isStrikeThrough": true
        },
        {
          "title": "11월 3일 (일) 00:00 / 입스위치 1 vs 1 레스터 시티",
          "link": "https://m.sports.naver.com/game/2024110310050850151/record",
          "isStrikeThrough": true
        },
        {
          "title": "11월 3일 (일) 00:00 / 리버풀 2 vs 1 브라이튼",
          "link": "https://m.sports.naver.com/game/2024110310050850153/record",
          "isStrikeThrough": true
        },
        {
          "title": "11월 3일 (일) 00:00 / 노팅엄 포레스트 3 vs 0 웨스트햄",
          "link": "https://m.sports.naver.com/game/2024110310050850159/record",
          "isStrikeThrough": true
        },
        {
          "title": "11월 3일 (일) 00:00 / 사우샘프턴 1 vs 0 에버튼",
          "link": "https://m.sports.naver.com/game/2024110310050850161/record",
          "isStrikeThrough": true
        },
        {
          "title": "11월 3일 (일) 02:30 / 울버햄튼 2 vs 2 크리스털 팰리스",
          "link": "https://m.sports.naver.com/game/2024110310050850165/video",
          "isStrikeThrough": true
        },
        {
          "title": "11월 3일 (일) 23:00 / 토트넘 4 vs 1 빌라",
          "link": "https://m.sports.naver.com/game/2024110310050850163/video",
          "isStrikeThrough": true
        },
        {
          "title": "11월 4일 (월) 01:30 / 맨유 1 vs 1 첼시",
          "link": "https://m.sports.naver.com/game/2024110410050850155/video",
          "isStrikeThrough": true
        },
        {
          "title": "11월 5일 (화) 05:00 / 풀럼 2 vs 1 브렌트포드",
          "link": "https://m.sports.naver.com/game/2024110510050850149/record",
          "isStrikeThrough": true
        },
        {
          "title": "11월 10일 (일) 00:00 / 브렌트퍼드 vs 본머스",
          "link": "https://m.sports.naver.com/game/2024111010050850167/preview",
          "isStrikeThrough": false
        },
        {
          "title": "11월 10일 (일) 00:00 / 팰리스 vs 풀럼",
          "link": "https://m.sports.naver.com/game/2024111010050850173/preview",
          "isStrikeThrough": false
        },
        {
          "title": "11월 10일 (일) 00:00 / 웨스트햄 vs 에버턴",
          "link": "https://m.sports.naver.com/game/2024111010050850183/preview",
          "isStrikeThrough": false
        },
        {
          "title": "11월 10일 (일) 00:00 / 울버햄튼 vs 사우샘프턴",
          "link": "https://m.sports.naver.com/game/2024111010050850185/preview",
          "isStrikeThrough": false
        },
        {
          "title": "11월 10일 (일) 02:30 / 브라이턴 vs 맨시티",
          "link": "https://m.sports.naver.com/game/2024111010050850169/preview",
          "isStrikeThrough": false
        },
        {
          "title": "11월 10일 (일) 05:00 / 리버풀 vs 애스턴빌라",
          "link": "https://m.sports.naver.com/game/2024111010050850175/preview",
          "isStrikeThrough": false
        },
        {
          "title": "11월 10일 (일) 23:00 / 맨유 vs 레스터",
          "link": "https://m.sports.naver.com/game/2024111010050850177/preview",
          "isStrikeThrough": false
        },
        {
          "title": "11월 10일 (일) 23:00 / 노팅엄 vs 뉴캐슬",
          "link": "https://m.sports.naver.com/game/2024111010050850179/preview",
          "isStrikeThrough": false
        },
        {
          "title": "11월 10일 (일) 23:00 / 토트넘 vs 입스위치",
          "link": "https://m.sports.naver.com/game/2024111010050850181/preview",
          "isStrikeThrough": false
        },
        {
          "title": "11월 11일 (월) 01:30 / 첼시 vs 아스널",
          "link": "https://m.sports.naver.com/game/2024111110050850171/preview",
          "isStrikeThrough": false
        },
        {
          "title": "11월 23일 (토) 21:30 / 레스터 vs 첼시",
          "link": "https://m.sports.naver.com/game/2024112310050850199/preview",
          "isStrikeThrough": false
        },
        {
          "title": "11월 24일 (일) 00:00 / 본머스 vs 브라이턴",
          "link": "https://m.sports.naver.com/game/2024112410050850187/preview",
          "isStrikeThrough": false
        },
        {
          "title": "11월 24일 (일) 00:00 / 아스널 vs 노팅엄",
          "link": "https://m.sports.naver.com/game/2024112410050850189/preview",
          "isStrikeThrough": false
        },
        {
          "title": "11월 24일 (일) 00:00 / 애스턴빌라 vs 팰리스",
          "link": "https://m.sports.naver.com/game/2024112410050850191/preview",
          "isStrikeThrough": false
        },
        {
          "title": "11월 24일 (일) 00:00 / 에버턴 vs 브렌트퍼드",
          "link": "https://m.sports.naver.com/game/2024112410050850193/preview",
          "isStrikeThrough": false
        },
        {
          "title": "11월 24일 (일) 00:00 / 풀럼 vs 울버햄튼",
          "link": "https://m.sports.naver.com/game/2024112410050850195/preview",
          "isStrikeThrough": false
        },
        {
          "title": "11월 24일 (일) 02:30 / 맨시티 vs 토트넘",
          "link": "https://m.sports.naver.com/game/2024112410050850201/preview",
          "isStrikeThrough": false
        },
        {
          "title": "11월 24일 (일) 23:00 / 사우샘프턴 vs 리버풀",
          "link": "https://m.sports.naver.com/game/2024112410050850205/preview",
          "isStrikeThrough": false
        },
        {
          "title": "11월 25일 (월) 01:30 / 입스위치 vs 맨유",
          "link": "https://m.sports.naver.com/game/2024112510050850197/preview",
          "isStrikeThrough": false
        },
        {
          "title": "11월 26일 (화) 05:00 / 뉴캐슬 vs 웨스트햄",
          "link": "https://m.sports.naver.com/game/2024112610050850203/preview",
          "isStrikeThrough": false
        },
        {
          "title": "11월 30일 (토) 05:00 / 브라이턴 vs 사우샘프턴",
          "link": "https://m.sports.naver.com/game/2024113010050850209/preview",
          "isStrikeThrough": false
        }
      ]
    },
    {
      "name": "라리가 일정",
      "url": "https://m.sports.naver.com/wfootball/schedule/index?category=primera",
      "category": "sports",
      "data": [
        {
          "title": "11월 2일 (토) 05:00 / 알라베스 1 vs 0 마요르카",
          "link": "https://m.sports.naver.com/game/2024110265050852311/record",
          "isStrikeThrough": true
        },
        {
          "title": "11월 2일 (토) 22:00 / 오사수나 1 vs 0 바야돌리드",
          "link": "https://m.sports.naver.com/game/2024110265050852309/record",
          "isStrikeThrough": true
        },
        {
          "title": "11월 3일 (일) 00:15 / 지로나 4 vs 3 레가네스",
          "link": "https://m.sports.naver.com/game/2024110365050852307/record",
          "isStrikeThrough": true
        },
        {
          "title": "11월 3일 (일) 02:30 / 비야레알 vs 바예카노",
          "link": "https://m.sports.naver.com/game/2024110365050852313/preview",
          "isStrikeThrough": false
        },
        {
          "title": "11월 3일 (일) 05:00 / 발렌시아 vs 레알 마드리드",
          "link": "https://m.sports.naver.com/game/2024110365050852315/preview",
          "isStrikeThrough": false
        },
        {
          "title": "11월 3일 (일) 22:00 / At. 마드리드 2 vs 0 라스팔마스",
          "link": "https://m.sports.naver.com/game/2024110365050852303/record",
          "isStrikeThrough": true
        },
        {
          "title": "11월 4일 (월) 00:15 / 바르셀로나 3 vs 1 에스파뇰",
          "link": "https://m.sports.naver.com/game/2024110465050852319/video",
          "isStrikeThrough": true
        },
        {
          "title": "11월 4일 (월) 02:30 / 세비야 0 vs 2 소시에다드",
          "link": "https://m.sports.naver.com/game/2024110465050852317/record",
          "isStrikeThrough": true
        },
        {
          "title": "11월 4일 (월) 05:00 / 빌바오 1 vs 1 베티스",
          "link": "https://m.sports.naver.com/game/2024110465050852301/record",
          "isStrikeThrough": true
        },
        {
          "title": "11월 5일 (화) 05:00 / 셀타 데 비고 1 vs 0 헤타페",
          "link": "https://m.sports.naver.com/game/2024110565050852305/record",
          "isStrikeThrough": true
        },
        {
          "title": "11월 9일 (토) 05:00 / 바예카노 vs 라스팔마스",
          "link": "https://m.sports.naver.com/game/2024110965050852337/preview",
          "isStrikeThrough": false
        },
        {
          "title": "11월 9일 (토) 22:00 / 레알 마드리드 vs 오사수나",
          "link": "https://m.sports.naver.com/game/2024110965050852335/preview",
          "isStrikeThrough": false
        },
        {
          "title": "11월 10일 (일) 00:15 / 비야레알 vs 알라베스",
          "link": "https://m.sports.naver.com/game/2024111065050852339/preview",
          "isStrikeThrough": false
        },
        {
          "title": "11월 10일 (일) 02:30 / 에스파뇰 vs 발렌시아",
          "link": "https://m.sports.naver.com/game/2024111065050852327/preview",
          "isStrikeThrough": false
        },
        {
          "title": "11월 10일 (일) 05:00 / 레가네스 vs 세비야",
          "link": "https://m.sports.naver.com/game/2024111065050852325/preview",
          "isStrikeThrough": false
        },
        {
          "title": "11월 10일 (일) 22:00 / 레알 베티스 vs 셀타 비고",
          "link": "https://m.sports.naver.com/game/2024111065050852321/preview",
          "isStrikeThrough": false
        },
        {
          "title": "11월 11일 (월) 00:15 / 마요르카 vs AT 마드리드",
          "link": "https://m.sports.naver.com/game/2024111165050852331/preview",
          "isStrikeThrough": false
        },
        {
          "title": "11월 11일 (월) 02:30 / 헤타페 vs 지로나",
          "link": "https://m.sports.naver.com/game/2024111165050852323/preview",
          "isStrikeThrough": false
        },
        {
          "title": "11월 11일 (월) 02:30 / 레알 바야돌리드 vs 아틀레틱",
          "link": "https://m.sports.naver.com/game/2024111165050852329/preview",
          "isStrikeThrough": false
        },
        {
          "title": "11월 11일 (월) 05:00 / 레알 소시에다드 vs 바르셀로나",
          "link": "https://m.sports.naver.com/game/2024111165050852333/preview",
          "isStrikeThrough": false
        },
        {
          "title": "11월 23일 (토) 05:00 / 헤타페 vs 레알 바야돌리드",
          "link": "https://m.sports.naver.com/game/2024112365050852343/preview",
          "isStrikeThrough": false
        },
        {
          "title": "11월 23일 (토) 22:00 / 발렌시아 vs 레알 베티스",
          "link": "https://m.sports.naver.com/game/2024112365050852353/preview",
          "isStrikeThrough": false
        },
        {
          "title": "11월 24일 (일) 00:15 / AT 마드리드 vs 알라베스",
          "link": "https://m.sports.naver.com/game/2024112465050852357/preview",
          "isStrikeThrough": false
        },
        {
          "title": "11월 24일 (일) 02:30 / 라스팔마스 vs 마요르카",
          "link": "https://m.sports.naver.com/game/2024112465050852347/preview",
          "isStrikeThrough": false
        },
        {
          "title": "11월 24일 (일) 02:30 / 지로나 vs 에스파뇰",
          "link": "https://m.sports.naver.com/game/2024112465050852359/preview",
          "isStrikeThrough": false
        },
        {
          "title": "11월 24일 (일) 05:00 / 셀타 비고 vs 바르셀로나",
          "link": "https://m.sports.naver.com/game/2024112465050852351/preview",
          "isStrikeThrough": false
        },
        {
          "title": "11월 24일 (일) 22:00 / 오사수나 vs 비야레알",
          "link": "https://m.sports.naver.com/game/2024112465050852345/preview",
          "isStrikeThrough": false
        },
        {
          "title": "11월 25일 (월) 00:15 / 세비야 vs 바예카노",
          "link": "https://m.sports.naver.com/game/2024112565050852355/preview",
          "isStrikeThrough": false
        },
        {
          "title": "11월 25일 (월) 02:30 / 레가네스 vs 레알 마드리드",
          "link": "https://m.sports.naver.com/game/2024112565050852349/preview",
          "isStrikeThrough": false
        },
        {
          "title": "11월 25일 (월) 05:00 / 아틀레틱 vs 레알 소시에다드",
          "link": "https://m.sports.naver.com/game/2024112565050852341/preview",
          "isStrikeThrough": false
        }
      ]
    }
  ]
}